azure/mgmt/computefleet/__init__.py
azure/mgmt/computefleet/_client.py
azure/mgmt/computefleet/_configuration.py
azure/mgmt/computefleet/_model_base.py
azure/mgmt/computefleet/_patch.py
azure/mgmt/computefleet/_serialization.py
azure/mgmt/computefleet/_version.py
azure/mgmt/computefleet/py.typed
azure/mgmt/computefleet/aio/__init__.py
azure/mgmt/computefleet/aio/_client.py
azure/mgmt/computefleet/aio/_configuration.py
azure/mgmt/computefleet/aio/_patch.py
azure/mgmt/computefleet/aio/operations/__init__.py
azure/mgmt/computefleet/aio/operations/_operations.py
azure/mgmt/computefleet/aio/operations/_patch.py
azure/mgmt/computefleet/models/__init__.py
azure/mgmt/computefleet/models/_enums.py
azure/mgmt/computefleet/models/_models.py
azure/mgmt/computefleet/models/_patch.py
azure/mgmt/computefleet/operations/__init__.py
azure/mgmt/computefleet/operations/_operations.py
azure/mgmt/computefleet/operations/_patch.py
azure_mgmt_computefleet-1.0.0.dist-info/LICENSE
azure_mgmt_computefleet-1.0.0.dist-info/METADATA
azure_mgmt_computefleet-1.0.0.dist-info/WHEEL
azure_mgmt_computefleet-1.0.0.dist-info/top_level.txt
azure_mgmt_computefleet-1.0.0.dist-info/RECORD
